[{
  "topicTitle"  : "Layout",
  "routeName"   : "/layoutExamples",
  "contentList" : [
    {
      "contentTitle": "Column and Row",
      "routeName": "/basicColumnRow"
    },
    {
      "contentTitle": "Grid View",
      "routeName": "/gridView"
    },
    {
      "contentTitle": "List View",
      "routeName": "/listView"
  }]
  },{
  "topicTitle"  : "Animations",
  "routeName"   : "/animations",
  "contentList" :[
    {
      "contentTitle": "Animated List",
      "routeName": "/animatedList"
    },
    {
      "contentTitle": "Fade Demo",
      "routeName": "/fadeDemo"
    }]
},
  {
    "topicTitle"  : "Designs",
    "routeName"   : "/designs",
    "contentList" : [
      {
        "contentTitle": "Drawer Demo",
        "routeName"   : "/drawer"
      },
      {
        "contentTitle": "SnackBar Demo",
        "routeName"   : "/snackDemo"
      },
      {
        "contentTitle": "TabBar Demo",
        "routeName"   : "/tabbarDemo"
      }
    ]
  },
  {
    "topicTitle"  : "Navigation",
    "routeName"   : "/navigation",
    "contentList" : [
      {
        "contentTitle": "Widget Transition",
        "routeName"   : "/widgetTransition"
      },
      {
        "contentTitle": "Navigate To and Back",
        "routeName"   : "/navigateToAndFrom"
      },
      {
        "contentTitle": "Return Data",
        "routeName"   : "/bringBackData"
      }
    ]
  },
  {
    "topicTitle"  : "Network",
    "routeName"   : "/network",
    "contentList" : [
      {
        "contentTitle": "Fetch Data",
        "routeName"   : "/fetchData"
      }
    ]
  }

]